stewai/__init__.py
stewai/client.py
stewai/errors.py
stewai/py.typed
stewai/types.py
stewai/resources/__init__.py
stewai/resources/runs.py
stewai/resources/storage.py
stewai-0.1.2.dist-info/METADATA
stewai-0.1.2.dist-info/WHEEL
stewai-0.1.2.dist-info/licenses/LICENSE.md
stewai-0.1.2.dist-info/RECORD
