Metadata-Version: 2.4
Name: stewai
Version: 0.1.2
Summary: Official StewAI Python SDK
Author-email: StewAI <dev@stewai.com>
License: StewAI Commercial License
License-File: LICENSE.md
Keywords: api,sdk,stewai
Classifier: Development Status :: 3 - Alpha
Classifier: License :: Other/Proprietary License
Classifier: Programming Language :: Python :: 3
Classifier: Programming Language :: Python :: 3 :: Only
Classifier: Typing :: Typed
Requires-Python: >=3.10
Requires-Dist: httpx<1.0,>=0.27
Provides-Extra: dev
Requires-Dist: pytest<9,>=8; extra == 'dev'
